specAugment/__init__.py
specAugment/sparse_image_warp_pytorch.py
specAugment/sparse_image_warp_zcaceres.py
specAugment/spec_augment.py
specAugment/spec_augment_pytorch.py
specAugment/spec_augment_tensorflow.py
specAugment/spec_augment_test.py
SpecAugment-1.2.5.dist-info/METADATA
SpecAugment-1.2.5.dist-info/WHEEL
SpecAugment-1.2.5.dist-info/top_level.txt
SpecAugment-1.2.5.dist-info/RECORD
