Metadata-Version: 2.1
Name: SpecAugment
Version: 1.2.5
Summary: A implementation of "SpecAugment"
Home-page: https://github.com/shelling203/SpecAugment
Author: UNKNOWN
Author-email: UNKNOWN
License: UNKNOWN
Platform: UNKNOWN
Requires-Dist: librosa
Requires-Dist: matplotlib
